flufl/enum/__init__.py
flufl/enum/_enum.py
flufl_enum-7.0.0.dist-info/METADATA
flufl_enum-7.0.0.dist-info/WHEEL
flufl_enum-7.0.0.dist-info/licenses/LICENSE
flufl_enum-7.0.0.dist-info/RECORD
