Metadata-Version: 2.4
Name: flufl.enum
Version: 7.0.0
Summary: A Python enumeration package
Project-URL: Home Page, https://fluflenum.readthedocs.io
Project-URL: Documentation, https://fluflenum.readthedocs.io
Project-URL: Source Code, https://gitlab.com/warsaw/flufl.enum.git
Project-URL: Bug Tracker, https://gitlab.com/warsaw/flufl.enum/issues
Author-email: Barry Warsaw <barry@python.org>
License: Apache-2.0
License-File: LICENSE
Keywords: enum
Classifier: Development Status :: 5 - Production/Stable
Classifier: Development Status :: 6 - Mature
Classifier: Intended Audience :: Developers
Classifier: License :: OSI Approved :: Apache Software License
Classifier: Operating System :: MacOS :: MacOS X
Classifier: Operating System :: Microsoft :: Windows
Classifier: Operating System :: POSIX
Classifier: Programming Language :: Python
Classifier: Programming Language :: Python :: 3
Classifier: Topic :: Software Development :: Libraries
Classifier: Topic :: Software Development :: Libraries :: Python Modules
Requires-Python: >=3.9
Requires-Dist: atpublic
Requires-Dist: typing-extensions>=4.6.0; python_version < '3.11'
